cazy_webscraper/__init__.py
cazy_webscraper/cazy_scraper.py
cazy_webscraper/api/__init__.py
cazy_webscraper/api/cw_query_database.py
cazy_webscraper/cache/__init__.py
cazy_webscraper/cache/cazy.py
cazy_webscraper/cache/ncbi.py
cazy_webscraper/cache/uniprot.py
cazy_webscraper/cazy/__init__.py
cazy_webscraper/crawler/__init__.py
cazy_webscraper/crawler/get_validation_data.py
cazy_webscraper/expand/__init__.py
cazy_webscraper/expand/extract_seqs/__init__.py
cazy_webscraper/expand/extract_seqs/extract_db_seqs.py
cazy_webscraper/expand/genbank/__init__.py
cazy_webscraper/expand/genbank/genomes/__init__.py
cazy_webscraper/expand/genbank/genomes/entrez.py
cazy_webscraper/expand/genbank/genomes/get_genome_accs.py
cazy_webscraper/expand/genbank/sequences/__init__.py
cazy_webscraper/expand/genbank/sequences/get_genbank_sequences.py
cazy_webscraper/expand/genbank/taxonomy/__init__.py
cazy_webscraper/expand/genbank/taxonomy/get_ncbi_taxs.py
cazy_webscraper/expand/gtdb/__init__.py
cazy_webscraper/expand/gtdb/get_gtdb_tax.py
cazy_webscraper/expand/pdb/__init__.py
cazy_webscraper/expand/pdb/get_pdb_structures.py
cazy_webscraper/expand/uniprot/__init__.py
cazy_webscraper/expand/uniprot/get_uniprot_data.py
cazy_webscraper/ncbi/__init__.py
cazy_webscraper/ncbi/gene_names/__init__.py
cazy_webscraper/ncbi/genomes/__init__.py
cazy_webscraper/ncbi/sequences/__init__.py
cazy_webscraper/ncbi/taxonomy/__init__.py
cazy_webscraper/ncbi/taxonomy/lineage.py
cazy_webscraper/ncbi/taxonomy/multiple_taxa.py
cazy_webscraper/sql/__init__.py
cazy_webscraper/sql/get_schema.py
cazy_webscraper/sql/sql_orm.py
cazy_webscraper/sql/sql_interface/__init__.py
cazy_webscraper/sql/sql_interface/add_data/__init__.py
cazy_webscraper/sql/sql_interface/add_data/add_cazyme_data.py
cazy_webscraper/sql/sql_interface/add_data/add_genbank_data.py
cazy_webscraper/sql/sql_interface/add_data/add_genome_data.py
cazy_webscraper/sql/sql_interface/add_data/add_gtdb_tax.py
cazy_webscraper-2.3.0.4.dist-info/LICENSE
cazy_webscraper-2.3.0.4.dist-info/METADATA
cazy_webscraper-2.3.0.4.dist-info/WHEEL
cazy_webscraper-2.3.0.4.dist-info/entry_points.txt
cazy_webscraper-2.3.0.4.dist-info/top_level.txt
cazy_webscraper-2.3.0.4.dist-info/RECORD
