Metadata-Version: 2.1
Name: cazy_webscraper
Version: 2.3.0.4
Summary: A tool to automate retrieving data from CAZy, build a local CAZyme SQL database, and throughly interrogating the data. Also, automate retrieving protein data, sequences, EC numbers and structure files for specific datasets in the CAZyme database from UniProt, GenBank and PDB.
Home-page: https://github.com/HobnobMancer/cazy_webscraper
Author: Emma E. M. Hobbs
Author-email: eemh1@st-andrews.ac.uk
License: MIT
Keywords: bioinforamtics protein webscraper
Platform: Posix
Platform: MacOS X
Classifier: Development Status :: 4 - Beta
Classifier: Environment :: Console
Classifier: Intended Audience :: Science/Research
Classifier: License :: OSI Approved :: MIT License
Classifier: Natural Language :: English
Classifier: Operating System :: POSIX :: Linux
Classifier: Operating System :: MacOS :: MacOS X
Classifier: Programming Language :: Python :: 3.8
Classifier: Topic :: Scientific/Engineering :: Bio-Informatics
License-File: LICENSE
Requires-Dist: biopython
Requires-Dist: bioservices>=1.11.0
Requires-Dist: mechanicalsoup
Requires-Dist: pandas
Requires-Dist: pyyaml
Requires-Dist: requests
Requires-Dist: saintBioutils>=0.0.25
Requires-Dist: sqlalchemy==1.4.20
Requires-Dist: tqdm
Requires-Dist: html5lib
